Metadata-Version: 1.0
Name: PyPLTHook
Version: 1.0.0.post3
Summary: PyPLTHook: PLTHook in Python
Home-page: https://github.com/NyaMisty/PyPLTHook
Author: NyaMisty
Author-email: misty@misty.moe
License: UNKNOWN
Platform: UNKNOWN
